seniordev/__init__.py
seniordev-0.1.0.dist-info/WHEEL
seniordev-0.1.0.dist-info/METADATA
seniordev-0.1.0.dist-info/RECORD
