Metadata-Version: 2.1
Name: seniordev
Version: 0.1.0
Summary: Add senior python dev for all projects - trust is here
Author: Dmitriy Komarovskiy
Author-email: dmitriy.komarovskiy@gmail.com
Requires-Python: >=3.6,<4.0
Classifier: Programming Language :: Python :: 3
Classifier: Programming Language :: Python :: 3.10
Classifier: Programming Language :: Python :: 3.6
Classifier: Programming Language :: Python :: 3.7
Classifier: Programming Language :: Python :: 3.8
Classifier: Programming Language :: Python :: 3.9
